intelligent_plant/__init__.py
intelligent_plant/app_store_client.py
intelligent_plant/data_core_client.py
intelligent_plant/http_client.py
intelligent_plant/ip_hist.py
intelligent_plant/session_manager.py
intelligent_plant/type_handler.py
intelligent_plant/utility.py
intelligent_plant-1.8.1.dist-info/LICENSE
intelligent_plant-1.8.1.dist-info/METADATA
intelligent_plant-1.8.1.dist-info/WHEEL
intelligent_plant-1.8.1.dist-info/top_level.txt
intelligent_plant-1.8.1.dist-info/RECORD
