Metadata-Version: 2.1
Name: intelligent_plant
Version: 1.8.1
Summary: A wrapper for the Intellinget Plant API
Home-page: https://github.com/intelligentplant/py-app-store-api
Author: Intelligent Plant
Author-email: support@intelligentplant.com
License-File: LICENSE
Requires-Dist: requests
Requires-Dist: pandas
